MANIFEST.in
README
setup.py
classroom/__init__.py
classroom/admin.py
classroom/managers.py
classroom/models.py
classroom/tests.py
classroom/urls.py
classroom/utils.py
classroom/views.py
classroom/templatetags/__init__.py
classroom/templatetags/classroom_tags.py
django_classroom.egg-info/PKG-INFO
django_classroom.egg-info/SOURCES.txt
django_classroom.egg-info/dependency_links.txt
django_classroom.egg-info/top_level.txt
django_classroom.egg-info/zip-safe